nds2utils/__init__.py
nds2utils/data_utils.py
nds2utils/make_interactive_svg.py
nds2utils/plot_utils.py
nds2utils/version.py
nds2utils-0.1.12.dist-info/LICENSE
nds2utils-0.1.12.dist-info/METADATA
nds2utils-0.1.12.dist-info/WHEEL
nds2utils-0.1.12.dist-info/top_level.txt
nds2utils-0.1.12.dist-info/RECORD
