Metadata-Version: 2.1
Name: nds2utils
Version: 0.1.12
Summary: nds2 utilities for reading LIGO data quickly and easily
Home-page: https://git.ligo.org/craig-cahillane/nds2utils
Author: Craig Cahillane
Author-email: ccahilla@caltech.edu
Classifier: Programming Language :: Python :: 3
Classifier: License :: OSI Approved :: MIT License
Classifier: Operating System :: OS Independent
Requires-Python: >=3.6
License-File: LICENSE
